peslac/__init__.py
peslac/api_client.py
peslac/config.py
peslac-0.1.4.dist-info/METADATA
peslac-0.1.4.dist-info/WHEEL
peslac-0.1.4.dist-info/top_level.txt
peslac-0.1.4.dist-info/RECORD
