Metadata-Version: 2.2
Name: peslac
Version: 0.1.4
Summary: A Python package for the Peslac API
Home-page: https://github.com/peslacai/peslac-python
Author: Jibril Kala
Author-email: support@peslac.com
Project-URL: Bug Tracker, https://github.com/peslacai/peslac-python/issues
Project-URL: Source Code, https://github.com/peslacai/peslac-python
Project-URL: Documentation, https://github.com/peslacai/peslac-python#readme
Keywords: peslac,api,documents,tools,nodejs,rag,ai,llm,remote-file,remote-file-processing,document-processing,file-processing,ocr,image-processing,pdf-processing,document-ocr,image-ocr,pdf-ocr,pdf-splitter,pdf-merger
Classifier: Programming Language :: Python :: 3
Classifier: License :: OSI Approved :: MIT License
Classifier: Operating System :: OS Independent
Classifier: Intended Audience :: Developers
Classifier: Topic :: Software Development :: Libraries :: Python Modules
Classifier: Topic :: Text Processing :: General
Requires-Python: >=3.7
Requires-Dist: requests
Requires-Dist: requests-toolbelt
Dynamic: author
Dynamic: author-email
Dynamic: classifier
Dynamic: description
Dynamic: description-content-type
Dynamic: home-page
Dynamic: keywords
Dynamic: project-url
Dynamic: requires-dist
Dynamic: requires-python
Dynamic: summary
